{
  "oxfam":
    {
        "no_match": "Help save children's lives",
        "amounts":
        {
          "5": "Buy %quantity% vaccine$",
          "10": "Buy %quantity% mosquito net$",
          "20": "Get %quantity% goat$ for a poor family in Uganda",
          "50": "Allow %quantity% farmer$ not to cut down their trees",
          "100": "Build %quantity% school$"
        }
    },

  "tree_hughers_international":
    {
        "no_match": "Help save animals' lives",
        "amounts":
        {
          "5": "Save %quantity% mouse$mice$",
          "10": "Save %quantity% wolf$wolves$",
          "20": "Save %quantity% rhino$",
          "50": "Save %quantity% elephant$",
          "100": "Save %quantity% whale$"
        }
    }
}
